lucian_first_project/__init__.py
lucian_first_project-0.1.0.dist-info/METADATA
lucian_first_project-0.1.0.dist-info/top_level.txt
lucian_first_project-0.2.0.dist-info/METADATA
lucian_first_project-0.2.0.dist-info/WHEEL
lucian_first_project-0.2.0.dist-info/top_level.txt
lucian_first_project-0.2.0.dist-info/RECORD
