Metadata-Version: 2.1
Name: lucian-first-project
Version: 0.2.0
Summary: Says Hello from Lucian
Author: Lucian Tudosia
Author-email: luciantudosia04@gmail.com
License: UNKNOWN
Platform: UNKNOWN
Requires-Dist: dinosay
